{
	"description": "项目配置文件",
	"packOptions": {
		"ignore": []
	},
	"setting": {
		"urlCheck": true,
		"es6": true,
		"postcss": true,
		"minified": true,
		"newFeature": true,
		"autoAudits": false
	},
	"compileType": "miniprogram",
	"libVersion": "2.5.0",
	"appid": "wxf5ef8d660a1234db",
	"projectname": "Ai%E5%B1%95%E7%A4%BA%E5%B0%8F%E7%A8%8B%E5%BA%8F",
	"debugOptions": {
		"hidedInDevtools": []
	},
	"isGameTourist": false,
	"simulatorType": "wechat",
	"simulatorPluginLibVersion": {},
	"condition": {
		"search": {
			"current": -1,
			"list": []
		},
		"conversation": {
			"current": -1,
			"list": []
		},
		"plugin": {
			"current": -1,
			"list": []
		},
		"game": {
			"currentL": -1,
			"list": []
		},
		"miniprogram": {
			"current": 1,
			"list": [
				{
					"id": -1,
					"name": "上传图片",
					"pathName": "pages/ocrDetail/index",
					"query": ""
				},
				{
					"id": -1,
					"name": "图片特效",
					"pathName": "pages/pictureDetail/index"
				}
			]
		}
	}
}